helloworld/__init__.py
helloworld/myhello.py
HelloWorldBasic-0.0.1.dist-info/METADATA
HelloWorldBasic-0.0.1.dist-info/WHEEL
HelloWorldBasic-0.0.1.dist-info/top_level.txt
HelloWorldBasic-0.0.1.dist-info/RECORD
