Metadata-Version: 2.1
Name: HelloWorldBasic
Version: 0.0.1
Summary: short desc here
Author: Mariano Rico
Author-email: <marstab4@gmail.com>
Keywords: python,hello
Classifier: Development Status :: 1 - Planning
Classifier: Intended Audience :: Developers
Classifier: Programming Language :: Python :: 3
Classifier: Operating System :: Unix
Classifier: Operating System :: MacOS :: MacOS X
Classifier: Operating System :: Microsoft :: Windows
